{
	"parent": "block/block",
    "textures": {
        "0": "block/basalt_side",
        "1": "block/barrel_bottom",
        "2": "block/anvil",
        "particle": "block/basalt_side"
    },
    "elements": [
        {
            "name": "base",
            "from": [ 4.0, 0.0, 4.0 ], 
            "to": [ 12.0, 3.0, 12.0 ], 
            "faces": {
                "north": { "texture": "#0", "uv": [ 0.0, 0.0, 8.0, 3.0 ] },
                "east": { "texture": "#0", "uv": [ 0.0, 0.0, 8.0, 3.0 ] },
                "south": { "texture": "#0", "uv": [ 0.0, 0.0, 8.0, 3.0 ] },
                "west": { "texture": "#0", "uv": [ 0.0, 0.0, 8.0, 3.0 ] },
                "down": { "texture": "#0", "uv": [ 0.0, 0.0, 8.0, 8.0 ] }
            }
        },
        {
            "name": "mid",
            "from": [ 3.0, 3.0, 3.0 ], 
            "to": [ 13.0, 14.0, 13.0 ], 
            "faces": {
                "north": { "texture": "#0", "uv": [ 0.0, 0.0, 10.0, 11.0 ] },
                "east": { "texture": "#0", "uv": [ 0.0, 0.0, 10.0, 11.0 ] },
                "south": { "texture": "#0", "uv": [ 0.0, 0.0, 10.0, 11.0 ] },
                "west": { "texture": "#0", "uv": [ 0.0, 0.0, 10.0, 11.0 ] },
                "up": { "texture": "#0", "uv": [ 0.0, 0.0, 10.0, 10.0 ] },
                "down": { "texture": "#0", "uv": [ 0.0, 0.0, 10.0, 10.0 ] }
            }
        },
        {
            "name": "cap",
            "from": [ 4.5, 14.0, 4.5 ], 
            "to": [ 11.5, 15.0, 11.5 ], 
            "faces": {
                "north": { "texture": "#1", "uv": [ 0.0, 0.0, 7.0, 1.0 ] },
                "east": { "texture": "#1", "uv": [ 0.0, 0.0, 7.0, 1.0 ] },
                "south": { "texture": "#1", "uv": [ 0.0, 0.0, 7.0, 1.0 ] },
                "west": { "texture": "#1", "uv": [ 0.0, 0.0, 7.0, 1.0 ] },
                "up": { "texture": "#1", "uv": [ 0.0, 0.0, 7.0, 7.0 ] }
            }
        },
        {
            "name": "faceN",
            "from": [ 5.5, 8.0, 2.0 ], 
            "to": [ 10.5, 12.0, 3.0 ], 
            "faces": {
                "north": { "texture": "#2", "uv": [ 0.0, 0.0, 5.0, 4.0 ] },
                "east": { "texture": "#2", "uv": [ 0.0, 0.0, 1.0, 4.0 ] },
                "west": { "texture": "#2", "uv": [ 0.0, 0.0, 1.0, 4.0 ] },
                "up": { "texture": "#2", "uv": [ 0.0, 0.0, 5.0, 1.0 ] },
                "down": { "texture": "#2", "uv": [ 0.0, 0.0, 5.0, 1.0 ] }
            }
        },
        {
            "name": "faceS",
            "from": [ 5.5, 8.0, 13.0 ], 
            "to": [ 10.5, 12.0, 14.0 ], 
            "faces": {
                "east": { "texture": "#2", "uv": [ 0.0, 0.0, 1.0, 4.0 ] },
                "south": { "texture": "#2", "uv": [ 0.0, 0.0, 5.0, 4.0 ] },
                "west": { "texture": "#2", "uv": [ 0.0, 0.0, 1.0, 4.0 ] },
                "up": { "texture": "#2", "uv": [ 0.0, 0.0, 5.0, 1.0 ] },
                "down": { "texture": "#2", "uv": [ 0.0, 0.0, 5.0, 1.0 ] }
            }
        },
        {
            "name": "faceW",
            "from": [ 2.0, 8.0, 5.5 ], 
            "to": [ 3.0, 12.0, 10.5 ], 
            "faces": {
                "north": { "texture": "#2", "uv": [ 0.0, 0.0, 1.0, 4.0 ] },
                "south": { "texture": "#2", "uv": [ 0.0, 0.0, 1.0, 4.0 ] },
                "west": { "texture": "#2", "uv": [ 0.0, 0.0, 5.0, 4.0 ] },
                "up": { "texture": "#2", "uv": [ 0.0, 0.0, 1.0, 5.0 ] },
                "down": { "texture": "#2", "uv": [ 0.0, 0.0, 1.0, 5.0 ] }
            }
        },
        {
            "name": "faceE",
            "from": [ 13.0, 8.0, 5.5 ], 
            "to": [ 14.0, 12.0, 10.5 ], 
            "faces": {
                "north": { "texture": "#2", "uv": [ 0.0, 0.0, 1.0, 4.0 ] },
                "east": { "texture": "#2", "uv": [ 0.0, 0.0, 5.0, 4.0 ] },
                "south": { "texture": "#2", "uv": [ 0.0, 0.0, 1.0, 4.0 ] },
                "up": { "texture": "#2", "uv": [ 0.0, 0.0, 1.0, 5.0 ] },
                "down": { "texture": "#2", "uv": [ 0.0, 0.0, 1.0, 5.0 ] }
            }
        }
    ]
}